{
  "root" : {
    "__class" : "RootNode",
    "children" : [
      {
        "__class" : "FrameNode",
        "aspectRatio" : null,
        "blendingEnabled" : 0,
        "blendingMode" : "normal",
        "bottom" : null,
        "centerAnchorX" : 0,
        "centerAnchorY" : 0,
        "children" : [
          {
            "__class" : "ShapeContainerNode",
            "autoSize" : true,
            "bottom" : null,
            "centerAnchorX" : 0.5,
            "centerAnchorY" : 0.46875,
            "children" : [
              {
                "__class" : "PathNode",
                "aspectRatio" : null,
                "exportOptions" : [

                ],
                "fillColor" : "#CCC",
                "fillEnabled" : true,
                "fillImage" : null,
                "fillImageOriginalName" : null,
                "fillImagePixelHeight" : null,
                "fillImagePixelWidth" : null,
                "fillImageResize" : "fill",
                "fillLinearGradient" : {
                  "__class" : "LinearGradient",
                  "alpha" : 1,
                  "angle" : 152,
                  "stops" : [
                    {
                      "__class" : "GradientColorStop",
                      "position" : 0,
                      "value" : "rgb(176, 107, 255)"
                    },
                    {
                      "__class" : "GradientColorStop",
                      "position" : 1,
                      "value" : "#6C10C1"
                    }
                  ]
                },
                "fillRadialGradient" : {
                  "__class" : "RadialGradient",
                  "alpha" : 1,
                  "centerAnchorX" : 0.5,
                  "centerAnchorY" : 0.5,
                  "heightFactor" : 0.5,
                  "stops" : [
                    {
                      "__class" : "GradientColorStop",
                      "position" : 0,
                      "value" : "rgb(176, 107, 255)"
                    },
                    {
                      "__class" : "GradientColorStop",
                      "position" : 1,
                      "value" : "#6C10C1"
                    }
                  ],
                  "widthFactor" : 0.5
                },
                "fillType" : "linear-gradient",
                "height" : 14.472135954999581,
                "id" : "nJq2fmYOR",
                "locked" : false,
                "name" : null,
                "opacity" : 1,
                "originalid" : null,
                "parentid" : "KLwCpzE89",
                "pathClosed" : true,
                "pathSegments" : [
                  {
                    "__class" : "PathSegment",
                    "handleInX" : 0,
                    "handleInY" : 0,
                    "handleMirroring" : "straight",
                    "handleOutX" : 0,
                    "handleOutY" : 0,
                    "radius" : 0,
                    "x" : 7.6084521303612274,
                    "y" : 0
                  },
                  {
                    "__class" : "PathSegment",
                    "handleInX" : 0,
                    "handleInY" : 0,
                    "handleMirroring" : "straight",
                    "handleOutX" : 0,
                    "handleOutY" : 0,
                    "radius" : 0,
                    "x" : 9.9595931395311208,
                    "y" : 4.7639320225002102
                  },
                  {
                    "__class" : "PathSegment",
                    "handleInX" : 0,
                    "handleInY" : 0,
                    "handleMirroring" : "straight",
                    "handleOutX" : 0,
                    "handleOutY" : 0,
                    "radius" : 0,
                    "x" : 15.216904260722458,
                    "y" : 5.5278640450004186
                  },
                  {
                    "__class" : "PathSegment",
                    "handleInX" : 0,
                    "handleInY" : 0,
                    "handleMirroring" : "straight",
                    "handleOutX" : 0,
                    "handleOutY" : 0,
                    "radius" : 0,
                    "x" : 11.412678195541844,
                    "y" : 9.236067977499788
                  },
                  {
                    "__class" : "PathSegment",
                    "handleInX" : 0,
                    "handleInY" : 0,
                    "handleMirroring" : "straight",
                    "handleOutX" : 0,
                    "handleOutY" : 0,
                    "radius" : 0,
                    "x" : 12.310734148701016,
                    "y" : 14.472135954999578
                  },
                  {
                    "__class" : "PathSegment",
                    "handleInX" : 0,
                    "handleInY" : 0,
                    "handleMirroring" : "straight",
                    "handleOutX" : 0,
                    "handleOutY" : 0,
                    "radius" : 0,
                    "x" : 7.6084521303612309,
                    "y" : 12
                  },
                  {
                    "__class" : "PathSegment",
                    "handleInX" : 0,
                    "handleInY" : 0,
                    "handleMirroring" : "straight",
                    "handleOutX" : 0,
                    "handleOutY" : 0,
                    "radius" : 0,
                    "x" : 2.9061701120214467,
                    "y" : 14.472135954999581
                  },
                  {
                    "__class" : "PathSegment",
                    "handleInX" : 0,
                    "handleInY" : 0,
                    "handleMirroring" : "straight",
                    "handleOutX" : 0,
                    "handleOutY" : 0,
                    "radius" : 0,
                    "x" : 3.8042260651806155,
                    "y" : 9.2360679774997916
                  },
                  {
                    "__class" : "PathSegment",
                    "handleInX" : 0,
                    "handleInY" : 0,
                    "handleMirroring" : "straight",
                    "handleOutX" : 0,
                    "handleOutY" : 0,
                    "radius" : 0,
                    "x" : 0,
                    "y" : 5.5278640450004239
                  },
                  {
                    "__class" : "PathSegment",
                    "handleInX" : 0,
                    "handleInY" : 0,
                    "handleMirroring" : "straight",
                    "handleOutX" : 0,
                    "handleOutY" : 0,
                    "radius" : 0,
                    "x" : 5.2573111211913357,
                    "y" : 4.7639320225002111
                  }
                ],
                "rotation" : 0,
                "visible" : true,
                "width" : 15.216904260722458,
                "x" : 0.39154786963877086,
                "y" : 0
              }
            ],
            "constraintsLocked" : false,
            "deviceType" : null,
            "exportIncludesBackground" : false,
            "exportOptions" : [

            ],
            "fillColor" : "#FFF",
            "fillEnabled" : false,
            "fillImage" : null,
            "fillImageOriginalName" : null,
            "fillImagePixelHeight" : null,
            "fillImagePixelWidth" : null,
            "fillImageResize" : "fill",
            "fillType" : "color",
            "height" : 15,
            "heightType" : 0,
            "id" : "KLwCpzE89",
            "left" : null,
            "locked" : false,
            "name" : null,
            "navigationTarget" : null,
            "navigationTransition" : "push",
            "navigationTransitionBackdropColor" : "rgba(4,4,15,.4)",
            "navigationTransitionDirection" : "left",
            "opacity" : 1,
            "originalid" : null,
            "parentid" : "mqh9FTxaB",
            "previewSettings" : null,
            "radius" : 0,
            "radiusBottomLeft" : 0,
            "radiusBottomRight" : 0,
            "radiusPerCorner" : false,
            "radiusTopLeft" : 0,
            "radiusTopRight" : 0,
            "right" : null,
            "sizeToFit" : true,
            "top" : null,
            "visible" : true,
            "width" : 16,
            "widthType" : 0
          }
        ],
        "clip" : true,
        "codeOverrideEnabled" : false,
        "constraintsLocked" : false,
        "deviceType" : null,
        "exportOptions" : [

        ],
        "fillColor" : "white",
        "fillEnabled" : true,
        "fillImage" : null,
        "fillImageOriginalName" : null,
        "fillImagePixelHeight" : null,
        "fillImagePixelWidth" : null,
        "fillImageResize" : "fill",
        "fillType" : "color",
        "guidesX" : [

        ],
        "guidesY" : [

        ],
        "height" : 16,
        "heightType" : 0,
        "id" : "mqh9FTxaB",
        "intrinsicHeight" : null,
        "intrinsicWidth" : null,
        "isExternalMaster" : null,
        "isMaster" : true,
        "isTarget" : false,
        "left" : 441,
        "locked" : false,
        "name" : "StarFilled",
        "navigationTarget" : null,
        "navigationTransition" : "push",
        "navigationTransitionBackdropColor" : "rgba(4,4,15,.4)",
        "navigationTransitionDirection" : "left",
        "opacity" : 1,
        "originalid" : null,
        "parentid" : "UIzipNs_b",
        "previewSettings" : null,
        "radius" : 0,
        "radiusBottomLeft" : 0,
        "radiusBottomRight" : 0,
        "radiusIsRelative" : false,
        "radiusPerCorner" : false,
        "radiusTopLeft" : 0,
        "radiusTopRight" : 0,
        "replicaInfo" : null,
        "right" : null,
        "rotation" : 0,
        "top" : 224,
        "visible" : true,
        "width" : 16,
        "widthType" : 0
      },
      {
        "__class" : "FrameNode",
        "aspectRatio" : null,
        "blendingEnabled" : 0,
        "blendingMode" : "normal",
        "bottom" : null,
        "centerAnchorX" : 0,
        "centerAnchorY" : 0,
        "children" : [
          {
            "__class" : "ShapeContainerNode",
            "autoSize" : true,
            "bottom" : null,
            "centerAnchorX" : 0.5,
            "centerAnchorY" : 0.5,
            "children" : [
              {
                "__class" : "StarShapeNode",
                "aspectRatio" : 1,
                "exportOptions" : [

                ],
                "fillColor" : "#e1e1e1",
                "fillEnabled" : true,
                "fillImage" : null,
                "fillImageOriginalName" : null,
                "fillImagePixelHeight" : null,
                "fillImagePixelWidth" : null,
                "fillImageResize" : "fill",
                "fillLinearGradient" : {
                  "__class" : "LinearGradient",
                  "alpha" : 1,
                  "angle" : 152,
                  "stops" : [
                    {
                      "__class" : "GradientColorStop",
                      "position" : 0,
                      "value" : "#e1e1e1"
                    },
                    {
                      "__class" : "GradientColorStop",
                      "position" : 1,
                      "value" : "#6C10C1"
                    }
                  ]
                },
                "fillRadialGradient" : {
                  "__class" : "RadialGradient",
                  "alpha" : 1,
                  "centerAnchorX" : 0.5,
                  "centerAnchorY" : 0.5,
                  "heightFactor" : 0.5,
                  "stops" : [
                    {
                      "__class" : "GradientColorStop",
                      "position" : 0,
                      "value" : "#e1e1e1"
                    },
                    {
                      "__class" : "GradientColorStop",
                      "position" : 1,
                      "value" : "#6C10C1"
                    }
                  ],
                  "widthFactor" : 0.5
                },
                "fillType" : "color",
                "height" : 16,
                "id" : "bmtIUqiSi",
                "locked" : false,
                "name" : null,
                "opacity" : 1,
                "originalid" : null,
                "parentid" : "GwkrB84ox",
                "radius" : 0,
                "rotation" : 0,
                "spikeCount" : 5,
                "spikeDepth" : 50,
                "visible" : true,
                "width" : 16,
                "x" : 0,
                "y" : 0
              }
            ],
            "constraintsLocked" : false,
            "deviceType" : null,
            "exportIncludesBackground" : false,
            "exportOptions" : [

            ],
            "fillColor" : "#FFF",
            "fillEnabled" : false,
            "fillImage" : null,
            "fillImageOriginalName" : null,
            "fillImagePixelHeight" : null,
            "fillImagePixelWidth" : null,
            "fillImageResize" : "fill",
            "fillType" : "color",
            "height" : 16,
            "heightType" : 0,
            "id" : "GwkrB84ox",
            "left" : null,
            "locked" : false,
            "name" : null,
            "navigationTarget" : null,
            "navigationTransition" : "push",
            "navigationTransitionBackdropColor" : "rgba(4,4,15,.4)",
            "navigationTransitionDirection" : "left",
            "opacity" : 1,
            "originalid" : null,
            "parentid" : "aeaqnIRLq",
            "previewSettings" : null,
            "radius" : 0,
            "radiusBottomLeft" : 0,
            "radiusBottomRight" : 0,
            "radiusPerCorner" : false,
            "radiusTopLeft" : 0,
            "radiusTopRight" : 0,
            "right" : null,
            "sizeToFit" : true,
            "top" : null,
            "visible" : true,
            "width" : 16,
            "widthType" : 0
          }
        ],
        "clip" : true,
        "codeOverrideEnabled" : false,
        "constraintsLocked" : false,
        "deviceType" : null,
        "exportOptions" : [

        ],
        "fillColor" : "white",
        "fillEnabled" : true,
        "fillImage" : null,
        "fillImageOriginalName" : null,
        "fillImagePixelHeight" : null,
        "fillImagePixelWidth" : null,
        "fillImageResize" : "fill",
        "fillType" : "color",
        "guidesX" : [

        ],
        "guidesY" : [

        ],
        "height" : 16,
        "heightType" : 0,
        "id" : "aeaqnIRLq",
        "intrinsicHeight" : null,
        "intrinsicWidth" : null,
        "isExternalMaster" : null,
        "isMaster" : true,
        "isTarget" : false,
        "left" : 469,
        "locked" : false,
        "name" : "StarEmpty",
        "navigationTarget" : null,
        "navigationTransition" : "push",
        "navigationTransitionBackdropColor" : "rgba(4,4,15,.4)",
        "navigationTransitionDirection" : "left",
        "opacity" : 1,
        "originalid" : null,
        "parentid" : "UIzipNs_b",
        "previewSettings" : null,
        "radius" : 0,
        "radiusBottomLeft" : 0,
        "radiusBottomRight" : 0,
        "radiusIsRelative" : false,
        "radiusPerCorner" : false,
        "radiusTopLeft" : 0,
        "radiusTopRight" : 0,
        "replicaInfo" : null,
        "right" : null,
        "rotation" : 0,
        "top" : 224,
        "visible" : true,
        "width" : 16,
        "widthType" : 0
      },
      {
        "__class" : "CodeComponentNode",
        "aspectRatio" : null,
        "bottom" : null,
        "centerAnchorX" : 0,
        "centerAnchorY" : 0,
        "children" : [

        ],
        "clip" : true,
        "codeComponentIdentifier" : ".\/App.tsx_App",
        "codeComponentProps" : {

        },
        "codeOverrideEnabled" : false,
        "constraintsLocked" : false,
        "deviceType" : null,
        "exportOptions" : [

        ],
        "fillColor" : "rgba(255,255,255,1)",
        "fillEnabled" : false,
        "fillImage" : null,
        "fillImageOriginalName" : null,
        "fillImagePixelHeight" : null,
        "fillImagePixelWidth" : null,
        "fillImageResize" : "fill",
        "fillType" : "color",
        "height" : 812,
        "heightType" : 0,
        "id" : "VMIigTjSW",
        "intrinsicHeight" : 812,
        "intrinsicWidth" : 375,
        "left" : -29,
        "locked" : false,
        "name" : null,
        "opacity" : 1,
        "originalid" : null,
        "parentid" : "UIzipNs_b",
        "previewSettings" : null,
        "radius" : 0,
        "radiusBottomLeft" : 0,
        "radiusBottomRight" : 0,
        "radiusIsRelative" : false,
        "radiusPerCorner" : false,
        "radiusTopLeft" : 0,
        "radiusTopRight" : 0,
        "right" : null,
        "rotation" : 0,
        "top" : -36,
        "visible" : true,
        "width" : 375,
        "widthType" : 0
      }
    ],
    "guidesX" : [

    ],
    "guidesY" : [

    ],
    "id" : "UIzipNs_b",
    "name" : null,
    "originalid" : null,
    "parentid" : null,
    "tokens" : {

    },
    "tokensIndex" : [

    ],
    "visible" : false
  },
  "version" : 55
}