{
  "root" : {
    "__class" : "RootNode",
    "children" : [
      {
        "__class" : "FrameNode",
        "aspectRatio" : null,
        "blendingEnabled" : 0,
        "blendingMode" : "normal",
        "bottom" : null,
        "centerAnchorX" : 0,
        "centerAnchorY" : 0,
        "children" : [
          {
            "__class" : "CodeComponentNode",
            "aspectRatio" : null,
            "bottom" : null,
            "centerAnchorX" : 0.5013333333333333,
            "centerAnchorY" : 0.16009852216748768,
            "children" : [

            ],
            "clip" : true,
            "codeComponentIdentifier" : ".\/Switch.tsx_Switch",
            "codeComponentProps" : {
              "isOn" : true
            },
            "codeOverrideEnabled" : true,
            "codeOverrideFile" : ".\/Examples.tsx",
            "codeOverrideIdentifier" : ".\/Examples.tsx_Switch",
            "codeOverrideName" : "Switch",
            "constraintsLocked" : false,
            "deviceType" : null,
            "exportOptions" : [

            ],
            "fillColor" : "rgba(255,255,255,1)",
            "fillEnabled" : false,
            "fillImage" : null,
            "fillImageOriginalName" : null,
            "fillImagePixelHeight" : null,
            "fillImagePixelWidth" : null,
            "fillImageResize" : "fill",
            "fillType" : "color",
            "height" : 32,
            "heightType" : 0,
            "id" : "ZjVjg8zT4",
            "intrinsicHeight" : 32,
            "intrinsicWidth" : 64,
            "left" : null,
            "locked" : false,
            "name" : null,
            "opacity" : 1,
            "originalid" : null,
            "parentid" : "Z9kKz24mz",
            "previewSettings" : null,
            "radius" : 0,
            "radiusBottomLeft" : 0,
            "radiusBottomRight" : 0,
            "radiusIsRelative" : false,
            "radiusPerCorner" : false,
            "radiusTopLeft" : 0,
            "radiusTopRight" : 0,
            "right" : null,
            "rotation" : 0,
            "top" : 114,
            "visible" : true,
            "width" : 64,
            "widthType" : 0
          }
        ],
        "clip" : true,
        "codeOverrideEnabled" : false,
        "constraintsLocked" : false,
        "deviceType" : "framer\/FramerAppleIPhoneXS",
        "exportOptions" : [

        ],
        "fillColor" : "rgba(255,255,255,1)",
        "fillEnabled" : true,
        "fillImage" : null,
        "fillImageOriginalName" : null,
        "fillImagePixelHeight" : null,
        "fillImagePixelWidth" : null,
        "fillImageResize" : "fill",
        "fillType" : "color",
        "guidesX" : [

        ],
        "guidesY" : [

        ],
        "height" : 812,
        "heightType" : 0,
        "id" : "Z9kKz24mz",
        "intrinsicHeight" : null,
        "intrinsicWidth" : null,
        "isExternalMaster" : null,
        "isMaster" : false,
        "isTarget" : false,
        "left" : 0,
        "locked" : false,
        "name" : null,
        "navigationTarget" : null,
        "navigationTransition" : "push",
        "navigationTransitionBackdropColor" : "rgba(4,4,15,.4)",
        "navigationTransitionDirection" : "left",
        "opacity" : 1,
        "originalid" : null,
        "parentid" : "UIzipNs_b",
        "previewSettings" : null,
        "radius" : 0,
        "radiusBottomLeft" : 0,
        "radiusBottomRight" : 0,
        "radiusIsRelative" : false,
        "radiusPerCorner" : false,
        "radiusTopLeft" : 0,
        "radiusTopRight" : 0,
        "replicaInfo" : null,
        "right" : null,
        "rotation" : 0,
        "top" : 0,
        "visible" : true,
        "width" : 375,
        "widthType" : 0
      }
    ],
    "guidesX" : [

    ],
    "guidesY" : [

    ],
    "id" : "UIzipNs_b",
    "name" : null,
    "originalid" : null,
    "parentid" : null,
    "tokens" : {

    },
    "tokensIndex" : [

    ],
    "visible" : false
  },
  "version" : 55
}